README.rst
setup.cfg
setup.py
rarog/__init__.py
rarog/core.py
rarog.egg-info/PKG-INFO
rarog.egg-info/SOURCES.txt
rarog.egg-info/dependency_links.txt
rarog.egg-info/requires.txt
rarog.egg-info/top_level.txt