Metadata-Version: 1.2
Name: rarog
Version: 0.1.dev0
Summary: Monitoring utility for machine learning experiments
Home-page: https://github.com/ikhlestov/rarog
Author: Illarion Khlestov
Author-email: khlyestovillarion@gmail.com
Maintainer: Illarion Khlestov
Maintainer-email: khlyestovillarion@gmail.com
License: Apache 2
Project-URL: Code, https://github.com/ikhlestov/rarog
Platform: UNKNOWN
Requires-Python: >=3.4.0
